tests/__init__.py
tests/test_whodis.py
whodis/__init__.py
whodis/common_filters.py
whodis/go_filters.py
whodis/java_filters.py
whodis/javascript_filters.py
whodis/python_filters.py
whodis/ruby_filters.py
whodis/whodis.py
whodis-1.0.2.dist-info/LICENSE
whodis-1.0.2.dist-info/METADATA
whodis-1.0.2.dist-info/WHEEL
whodis-1.0.2.dist-info/top_level.txt
whodis-1.0.2.dist-info/RECORD
