Metadata-Version: 2.1
Name: whodis
Version: 1.0.2
Summary: Parses the contents of a source code directory and determines the programming languages in use.
Home-page: https://github.com/irlrobot/whodis
Author: Josh Campbell
Author-email: josh@userdel.com
License: UNKNOWN
Platform: UNKNOWN
Classifier: Programming Language :: Python :: 3
Classifier: License :: OSI Approved :: MIT License
Classifier: Operating System :: OS Independent
